bytesparse/__init__.py
bytesparse/base.py
bytesparse/inplace.py
bytesparse/io.py
bytesparse-1.1.0.dist-info/licenses/AUTHORS.rst
bytesparse-1.1.0.dist-info/licenses/LICENSE
bytesparse-1.1.0.dist-info/METADATA
bytesparse-1.1.0.dist-info/WHEEL
bytesparse-1.1.0.dist-info/top_level.txt
bytesparse-1.1.0.dist-info/RECORD
