Metadata-Version: 2.4
Name: bytesparse
Version: 1.1.0
Summary: Library to handle sparse bytes within a virtual memory space
Author-email: Andrea Zoppi <texzk@email.it>
License-Expression: BSD-2-Clause
Project-URL: documentation, https://bytesparse.readthedocs.io
Project-URL: source, https://github.com/TexZK/bytesparse
Project-URL: tracker, https://github.com/TexZK/bytesparse/issues
Classifier: Development Status :: 5 - Production/Stable
Classifier: Intended Audience :: Developers
Classifier: Operating System :: OS Independent
Classifier: Programming Language :: Python
Classifier: Programming Language :: Python :: 3
Classifier: Programming Language :: Python :: 3 :: Only
Classifier: Programming Language :: Python :: 3.9
Classifier: Programming Language :: Python :: 3.10
Classifier: Programming Language :: Python :: 3.11
Classifier: Programming Language :: Python :: 3.12
Classifier: Programming Language :: Python :: 3.13
Classifier: Programming Language :: Python :: 3.14
Classifier: Programming Language :: Python :: Implementation :: CPython
Classifier: Programming Language :: Python :: Implementation :: PyPy
Classifier: Topic :: Scientific/Engineering :: Interface Engine/Protocol Translator
Classifier: Topic :: Software Development
Classifier: Topic :: Software Development :: Embedded Systems
Classifier: Topic :: Utilities
Requires-Python: >=3.9
License-File: LICENSE
License-File: AUTHORS.rst
Provides-Extra: testing
Requires-Dist: pytest; extra == "testing"
Dynamic: license-file
